{
  "$schema": "https://vega.github.io/schema/vega-lite/v2.json",
  "description": "Bar chart on brushing creates average y-value rule",
  "height": 400,
  "width": 600,
  "data": {
    "url": "seattle-weather.csv"
  },
  "layer": [
    {
      "selection": {
        "brush": {
          "type": "interval",
          "encodings": [
            "x"
          ]
        }
      },
      "mark": "bar",
      "encoding": {
        "x": {
          "field": "date",
          "type": "temporal",
          "timeUnit": "month"
        },
        "y": {
          "aggregate": "mean",
          "field": "precipitation",
          "type": "quantitative"
        }
      }
    },
    {
      "transform": [
        {
          "filter": {
            "selection": "brush"
          }
        }
      ],
      "mark": "rule",
      "encoding": {
        "y": {
          "aggregate": "mean",
          "field": "precipitation",
          "type": "quantitative"
        },
        "color": {
          "value": "red"
        },
        "size": {
          "value": 3
        }
      }
    }
  ]
}